{
    "asset": {
        "format": "png",
        "id": "c88db5ff5e77a11ff55b467cb85a82d7",
        "name": "5.png",
        "path": "file:C:/Users/developer/Desktop/doors/5.png",
        "size": {
            "width": 130,
            "height": 135
        },
        "state": 2,
        "type": 1
    },
    "regions": [
        {
            "id": "oFXoJ-RzJ",
            "type": "POLYGON",
            "tags": [
                "Door"
            ],
            "boundingBox": {
                "height": 63.85513804783331,
                "width": 58.081388234513945,
                "left": 39.69667451653446,
                "top": 29.719628307306877
            },
            "points": [
                {
                    "x": 39.69667451653446,
                    "y": 36.4486002699237
                },
                {
                    "x": 88.74006760149302,
                    "y": 29.719628307306877
                },
                {
                    "x": 97.7780627510484,
                    "y": 88.3177570093458
                },
                {
                    "x": 54.129446240905416,
                    "y": 93.57476635514018
                }
            ]
        }
    ],
    "version": "2.2.0"
}